{
  "Adriana Monreal Sanchez de Muniain": { "firstName": "Adriana", "lastName": "Monreal Sanchez de Muniain" },
  "Ane Muruzabal Saez de Jauregui": { "firstName": "Ane", "lastName": "Muruzabal Saez de Jauregui" },
  "Iñigo Yagüe Pérez de Obanos": { "firstName": "Iñigo", "lastName": "Yagüe Pérez de Obanos" },
  "Markel Yagüe Pérez de Obanos": { "firstName": "Markel", "lastName": "Yagüe Pérez de Obanos" },
  "Jon Osacar López de Armentia": { "firstName": "Jon", "lastName": "Osacar López de Armentia" },
  "Íñigo Osacar López de Armentia": { "firstName": "Íñigo", "lastName": "Osacar López de Armentia" },
  "Juan Monreal Sánchez de Monin": { "firstName": "Juan", "lastName": "Monreal Sánchez de Monin" },
  "Enara Fernandez de Ebarrena Oscoz": { "firstName": "Enara", "lastName": "Fernandez de Ebarrena Oscoz" },
  "Julen Fernández Ebarrena Oscoz": { "firstName": "Julen", "lastName": "Fernández Ebarrena Oscoz" },
  "Lucas amurrio (no puede miércoles) Quiere matricularse": { "firstName": "Lucas", "lastName": "Amurrio" },
  "Afonso De Jesús Silva Reis": { "firstName": "Afonso", "lastName": "De Jesús Silva Reis" },
  "Sara Lopez Iribarren velasco (lunes)": { "firstName": "Sara", "lastName": "Lopez Iribarren Velasco" }
}
